PyDuplicate/__init__.py
PyDuplicate/similarity.py
PyDuplicate-0.0.2.dist-info/LICENSE
PyDuplicate-0.0.2.dist-info/METADATA
PyDuplicate-0.0.2.dist-info/WHEEL
PyDuplicate-0.0.2.dist-info/top_level.txt
PyDuplicate-0.0.2.dist-info/RECORD
