Metadata-Version: 2.1
Name: PyDuplicate
Version: 0.0.2
Summary: Python functions for Efficient duplicate detection
Home-page: https://github.com/JeanBertinR/PyDuplicate
Author: Jean BERTIN
Author-email: <jeanbertin.ensam@gmail.com>
License: GPL-3.0
Keywords: Duplicate detection,Efficient duplicate search
Platform: UNKNOWN
Classifier: Development Status :: 1 - Planning
Classifier: Intended Audience :: Developers
Classifier: Programming Language :: Python :: 3
Classifier: Operating System :: Unix
Classifier: Operating System :: MacOS :: MacOS X
Classifier: Operating System :: Microsoft :: Windows
License-File: LICENSE
Requires-Dist: difflib
Requires-Dist: fuzzywuzzy
Requires-Dist: numpy
